FileChunker.py
__init__.py
__main__.py
pyfilechunker-0.1.1.dist-info/METADATA
pyfilechunker-0.1.1.dist-info/WHEEL
pyfilechunker-0.1.1.dist-info/entry_points.txt
pyfilechunker-0.1.1.dist-info/top_level.txt
pyfilechunker-0.1.1.dist-info/RECORD
