Metadata-Version: 2.4
Name: pyfilechunker
Version: 0.1.1
Summary: A utility to split large files into smaller chunks.
Author-email: Your Name <your.email@example.com>
Project-URL: Homepage, https://github.com/fxyzbtc/pyfilechunker
Project-URL: Repository, https://github.com/fxyzbtc/pyfilechunker
Classifier: Programming Language :: Python :: 3
Classifier: Operating System :: OS Independent
Classifier: Topic :: Utilities
Requires-Python: >=3.12
Requires-Dist: loguru>=0.7.3
Requires-Dist: pydantic>=2.11.3
Requires-Dist: tqdm>=4.67.1
Requires-Dist: typer>=0.12.5
